commands/__init__.py
commands/check.py
commands/delete.py
commands/init.py
core/__init__.py
core/config.py
core/container.py
core/exceptions.py
core/interfaces.py
core/models.py
improved_sdd-0.1.4.dist-info/licenses/LICENSE
services/__init__.py
services/cache_manager.py
services/file_tracker.py
services/github_downloader.py
services/template_resolver.py
ui/__init__.py
ui/console.py
ui/progress.py
improved_sdd-0.1.4.dist-info/METADATA
improved_sdd-0.1.4.dist-info/WHEEL
improved_sdd-0.1.4.dist-info/entry_points.txt
improved_sdd-0.1.4.dist-info/top_level.txt
improved_sdd-0.1.4.dist-info/RECORD
