Metadata-Version: 2.4
Name: improved-sdd
Version: 0.1.4
Summary: Setup tool for Improved Spec-Driven Development projects with AI assistant templates and GitLab Flow integration
Author-email: Robert Meisner <robert@catchit.pl>
License-Expression: MIT
Project-URL: Homepage, https://github.com/robertmeisner/improved-sdd
Project-URL: Repository, https://github.com/robertmeisner/improved-sdd
Project-URL: Issues, https://github.com/robertmeisner/improved-sdd/issues
Project-URL: Documentation, https://github.com/robertmeisner/improved-sdd#readme
Keywords: spec-driven-development,ai,github-copilot,templates,cli,development-tools,gitlab-flow,git-workflow
Classifier: Development Status :: 4 - Beta
Classifier: Intended Audience :: Developers
Classifier: Operating System :: OS Independent
Classifier: Programming Language :: Python :: 3
Classifier: Programming Language :: Python :: 3.9
Classifier: Programming Language :: Python :: 3.10
Classifier: Programming Language :: Python :: 3.11
Classifier: Programming Language :: Python :: 3.12
Classifier: Topic :: Software Development :: Libraries :: Python Modules
Classifier: Topic :: Software Development :: Code Generators
Classifier: Topic :: Utilities
Classifier: Environment :: Console
Requires-Python: >=3.9
License-File: LICENSE
Requires-Dist: typer>=0.9.0
Requires-Dist: rich>=13.0.0
Requires-Dist: platformdirs>=3.0.0
Requires-Dist: readchar>=4.0.0
Requires-Dist: httpx>=0.24.0
Provides-Extra: dev
Requires-Dist: flake8>=6.0.0; extra == "dev"
Requires-Dist: black>=23.0.0; extra == "dev"
Requires-Dist: isort>=5.12.0; extra == "dev"
Requires-Dist: pre-commit>=3.0.0; extra == "dev"
Requires-Dist: mypy>=1.0.0; extra == "dev"
Requires-Dist: safety>=2.0.0; extra == "dev"
Requires-Dist: bandit[toml]>=1.7.0; extra == "dev"
Requires-Dist: pip-audit>=2.0.0; extra == "dev"
Provides-Extra: test
Requires-Dist: pytest>=7.0.0; extra == "test"
Requires-Dist: pytest-asyncio>=0.21.0; extra == "test"
Requires-Dist: pytest-cov>=4.0.0; extra == "test"
Requires-Dist: pytest-mock>=3.10.0; extra == "test"
Requires-Dist: pytest-xdist>=3.0.0; extra == "test"
Requires-Dist: coverage>=7.0.0; extra == "test"
Dynamic: license-file
